pytest_ephemeral_container/__init__.py
pytest_ephemeral_container/py.typed
pytest_ephemeral_container-0.2.2.dist-info/METADATA
pytest_ephemeral_container-0.2.2.dist-info/WHEEL
pytest_ephemeral_container-0.2.2.dist-info/entry_points.txt
pytest_ephemeral_container-0.2.2.dist-info/RECORD
