Metadata-Version: 2.4
Name: pytest-ephemeral-container
Version: 0.2.2
Summary: Spawn epehemeral containers in pytest
License: Artistic-2.0
Author: Jamie Bliss
Author-email: jamie@teahouse.cafe
Requires-Python: >=3.10,<4.0
Classifier: License :: OSI Approved :: Artistic License
Classifier: Programming Language :: Python :: 3
Classifier: Programming Language :: Python :: 3.10
Classifier: Programming Language :: Python :: 3.11
Classifier: Programming Language :: Python :: 3.12
Classifier: Programming Language :: Python :: 3.13
Classifier: Programming Language :: Python :: 3.14
Requires-Dist: docker
Requires-Dist: pytest
Project-URL: source, https://codeberg.org/teahouse/pytest-ephemeral-container
